{
  "ticker": "AFCONS",
  "collected_at": "2026-07-10 05:34:41",
  "company_info": {
    "name": "Afcons Infrastructure Limited",
    "sector": "Industrials",
    "industry": "Engineering & Construction",
    "market_cap": 110703173632,
    "current_price": 301.0,
    "pe_ratio": 44.199707,
    "pb_ratio": 2.0259128,
    "roe": 0.04681,
    "debt_to_equity": 66.542,
    "revenue": 119483801600,
    "net_income": 2515000064,
    "eps": 6.81,
    "52_week_high": 479.4,
    "52_week_low": 265.8,
    "dividend_yield": 0.66
  }
}