{
  "ticker": "AHLEAST",
  "collected_at": "2026-06-29 06:15:45",
  "company_info": {
    "name": "Asian Hotels (East) Limited",
    "sector": "Consumer Cyclical",
    "industry": "Lodging",
    "market_cap": 2529775104,
    "current_price": 146.3,
    "pe_ratio": "N/A",
    "pb_ratio": 1.1089718,
    "roe": "N/A",
    "debt_to_equity": 154.746,
    "revenue": 1229206016,
    "net_income": -560804992,
    "eps": -32.45,
    "52_week_high": 175.3,
    "52_week_low": 127.25,
    "dividend_yield": 0.67
  }
}