{
  "ticker": "ANUP",
  "collected_at": "2026-06-23 05:42:18",
  "company_info": {
    "name": "The Anup Engineering Limited",
    "sector": "Industrials",
    "industry": "Specialty Industrial Machinery",
    "market_cap": 46673313792,
    "current_price": 2330.0,
    "pe_ratio": 42.425346,
    "pb_ratio": 6.755111,
    "roe": 0.16945,
    "debt_to_equity": 15.903,
    "revenue": 8222877184,
    "net_income": 1103923968,
    "eps": 54.92,
    "52_week_high": 2954.9,
    "52_week_low": 1422.3,
    "dividend_yield": 0.73
  }
}