{
  "ticker": "ASHAPURMIN",
  "collected_at": "2026-06-30 05:46:48",
  "company_info": {
    "name": "Ashapura Minechem Limited",
    "sector": "Basic Materials",
    "industry": "Other Industrial Metals & Mining",
    "market_cap": 63649038336,
    "current_price": 666.3,
    "pe_ratio": 15.864285,
    "pb_ratio": 3.8591857,
    "roe": 0.29049,
    "debt_to_equity": 87.774,
    "revenue": 52371300352,
    "net_income": 4014200064,
    "eps": 42.0,
    "52_week_high": 924.9,
    "52_week_low": 420.05,
    "dividend_yield": 0.15
  }
}