{
  "ticker": "AVANTIFEED",
  "collected_at": "2026-06-24 05:39:15",
  "company_info": {
    "name": "Avanti Feeds Limited",
    "sector": "Consumer Defensive",
    "industry": "Packaged Foods",
    "market_cap": 133370855424,
    "current_price": 978.9,
    "pe_ratio": 22.052265,
    "pb_ratio": 4.0553308,
    "roe": 0.19055,
    "debt_to_equity": 0.357,
    "revenue": 60658581504,
    "net_income": 6050165760,
    "eps": 44.39,
    "52_week_high": 1593.8,
    "52_week_low": 614.25,
    "dividend_yield": 0.91
  }
}