{
  "ticker": "BEL",
  "collected_at": "2026-07-23 04:54:40",
  "company_info": {
    "name": "Bharat Electronics Limited",
    "sector": "Industrials",
    "industry": "Aerospace & Defense",
    "market_cap": 2965577400320,
    "current_price": 405.7,
    "pe_ratio": 49.355232,
    "pb_ratio": 12.362494,
    "roe": 0.27556,
    "debt_to_equity": 0.273,
    "revenue": 276101103616,
    "net_income": 60620001280,
    "eps": 8.22,
    "52_week_high": 473.45,
    "52_week_low": 361.2,
    "dividend_yield": 1.06
  }
}