{
  "ticker": "BIMETAL",
  "collected_at": "2026-05-28 05:52:02",
  "company_info": {
    "name": "Bimetal Bearings Limited",
    "sector": "Consumer Cyclical",
    "industry": "Auto Parts",
    "market_cap": "N/A",
    "current_price": 572.15,
    "pe_ratio": 20.707565,
    "pb_ratio": 0.95315915,
    "roe": "N/A",
    "debt_to_equity": 0.368,
    "revenue": 2668163072,
    "net_income": 105602000,
    "eps": 27.63,
    "52_week_high": 632.3,
    "52_week_low": 470.9,
    "dividend_yield": "N/A"
  }
}