{
  "ticker": "BLACKBUCK",
  "collected_at": "2026-07-21 04:50:05",
  "company_info": {
    "name": "BlackBuck Limited",
    "sector": "Technology",
    "industry": "Software - Application",
    "market_cap": 103372742656,
    "current_price": 567.55,
    "pe_ratio": 64.862854,
    "pb_ratio": 7.288242,
    "roe": 0.12059,
    "debt_to_equity": 4.164,
    "revenue": 6519669760,
    "net_income": 1603430016,
    "eps": 8.75,
    "52_week_high": 748.0,
    "52_week_low": 428.7,
    "dividend_yield": "N/A"
  }
}