{
  "ticker": "CASTROLIND",
  "collected_at": "2026-06-24 05:41:45",
  "company_info": {
    "name": "Castrol India Limited",
    "sector": "Energy",
    "industry": "Oil & Gas Refining & Marketing",
    "market_cap": 185707724800,
    "current_price": 187.75,
    "pe_ratio": 19.39566,
    "pb_ratio": 9.772538,
    "roe": "N/A",
    "debt_to_equity": 3.305,
    "revenue": 58503598080,
    "net_income": 9586499584,
    "eps": 9.68,
    "52_week_high": 232.43,
    "52_week_low": 170.1,
    "dividend_yield": 4.71
  }
}