{
  "ticker": "CHAMBLFERT",
  "collected_at": "2026-06-11 06:21:20",
  "company_info": {
    "name": "Chambal Fertilisers and Chemicals Limited",
    "sector": "Basic Materials",
    "industry": "Agricultural Inputs",
    "market_cap": 189568630784,
    "current_price": 473.15,
    "pe_ratio": 9.701661,
    "pb_ratio": 1.8190591,
    "roe": 0.20451,
    "debt_to_equity": 10.274,
    "revenue": 207936602112,
    "net_income": 19533899776,
    "eps": 48.77,
    "52_week_high": 580.7,
    "52_week_low": 399.75,
    "dividend_yield": 2.09
  }
}