{
  "ticker": "CHOLAHLDNG",
  "collected_at": "2026-06-24 05:42:18",
  "company_info": {
    "name": "Cholamandalam Financial Holdings Limited",
    "sector": "Financial Services",
    "industry": "Credit Services",
    "market_cap": 300124733440,
    "current_price": 1598.3,
    "pe_ratio": 12.294616,
    "pb_ratio": 1.9422089,
    "roe": 0.18035,
    "debt_to_equity": 621.271,
    "revenue": 211424591872,
    "net_income": 24412899328,
    "eps": 130.0,
    "52_week_high": 2231.6,
    "52_week_low": 1305.0,
    "dividend_yield": 0.08
  }
}