{
  "ticker": "CINELINE",
  "collected_at": "2026-06-14 06:20:09",
  "company_info": {
    "name": "Cineline India Limited",
    "sector": "Communication Services",
    "industry": "Entertainment",
    "market_cap": 2720069376,
    "current_price": 79.38,
    "pe_ratio": 23.625,
    "pb_ratio": 1.7518151,
    "roe": 0.077259995,
    "debt_to_equity": 77.936,
    "revenue": 2366961920,
    "net_income": 115158000,
    "eps": 3.36,
    "52_week_high": 97.99,
    "52_week_low": 73.35,
    "dividend_yield": "N/A"
  }
}