{
  "ticker": "CLSEL",
  "collected_at": "2026-05-24 05:41:08",
  "company_info": {
    "name": "Chaman Lal Setia Exports Ltd.",
    "sector": "Consumer Defensive",
    "industry": "Packaged Foods",
    "market_cap": 13261822976,
    "current_price": 266.7,
    "pe_ratio": 13.125001,
    "pb_ratio": 1.7430918,
    "roe": "N/A",
    "debt_to_equity": 8.804,
    "revenue": 13788981248,
    "net_income": 1010652992,
    "eps": 20.32,
    "52_week_high": 395.75,
    "52_week_low": 203.75,
    "dividend_yield": 0.94
  }
}