{
  "ticker": "CONCORDBIO",
  "collected_at": "2026-06-01 06:33:52",
  "company_info": {
    "name": "Concord Biotech Limited",
    "sector": "Healthcare",
    "industry": "Biotechnology",
    "market_cap": 107922079744,
    "current_price": 1031.6,
    "pe_ratio": 41.58001,
    "pb_ratio": 5.9521337,
    "roe": 0.13543999,
    "debt_to_equity": 0.115,
    "revenue": 10548907008,
    "net_income": 2609059072,
    "eps": 24.81,
    "52_week_high": 2150.4,
    "52_week_low": 987.0,
    "dividend_yield": 1.02
  }
}