{
  "ticker": "CRIZAC",
  "collected_at": "2026-06-07 06:07:08",
  "company_info": {
    "name": "Crizac Limited",
    "sector": "Consumer Defensive",
    "industry": "Education & Training Services",
    "market_cap": 37512749056,
    "current_price": 214.38,
    "pe_ratio": 17.123003,
    "pb_ratio": 6.416834,
    "roe": 0.40003,
    "debt_to_equity": 0.31,
    "revenue": 10421570560,
    "net_income": 2191350016,
    "eps": 12.52,
    "52_week_high": 387.95,
    "52_week_low": 173.35,
    "dividend_yield": 7.46
  }
}