{
  "ticker": "DATAMATICS",
  "collected_at": "2026-06-28 06:01:39",
  "company_info": {
    "name": "Datamatics Global Services Limited",
    "sector": "Technology",
    "industry": "Information Technology Services",
    "market_cap": 47160987648,
    "current_price": 797.9,
    "pe_ratio": 24.274416,
    "pb_ratio": 3.0545018,
    "roe": 0.1348,
    "debt_to_equity": 14.384,
    "revenue": 19871500288,
    "net_income": 1942099968,
    "eps": 32.87,
    "52_week_high": 1120.0,
    "52_week_low": 615.6,
    "dividend_yield": 0.63
  }
}