{
  "ticker": "DATAPATTNS",
  "collected_at": "2026-06-29 06:22:05",
  "company_info": {
    "name": "Data Patterns (India) Limited",
    "sector": "Industrials",
    "industry": "Aerospace & Defense",
    "market_cap": 248552030208,
    "current_price": 4439.7,
    "pe_ratio": 91.220474,
    "pb_ratio": 14.322261,
    "roe": 0.1673,
    "debt_to_equity": 0.304,
    "revenue": 9247699968,
    "net_income": 2713700096,
    "eps": 48.67,
    "52_week_high": 4955.9,
    "52_week_low": 2131.0,
    "dividend_yield": 0.22
  }
}