{
  "ticker": "EFCIL",
  "collected_at": "2026-05-30 05:18:54",
  "company_info": {
    "name": "EFC (I) Limited",
    "sector": "Real Estate",
    "industry": "Real Estate Services",
    "market_cap": 26695405568,
    "current_price": 180.44,
    "pe_ratio": 11.471075,
    "pb_ratio": 2.8865783,
    "roe": "N/A",
    "debt_to_equity": 160.926,
    "revenue": 9548107776,
    "net_income": 1767464960,
    "eps": 15.73,
    "52_week_high": 357.0,
    "52_week_low": 171.55,
    "dividend_yield": "N/A"
  }
}