{
  "ticker": "EVERESTIND",
  "collected_at": "2026-06-16 07:08:49",
  "company_info": {
    "name": "Everest Industries Limited",
    "sector": "Industrials",
    "industry": "Building Products & Equipment",
    "market_cap": 5660504064,
    "current_price": 357.0,
    "pe_ratio": "N/A",
    "pb_ratio": 1.1446747,
    "roe": -0.18639,
    "debt_to_equity": 45.885,
    "revenue": 14169984000,
    "net_income": -1016870016,
    "eps": -64.19,
    "52_week_high": 750.0,
    "52_week_low": 284.9,
    "dividend_yield": 0.72
  }
}