{
  "ticker": "FACT",
  "collected_at": "2026-06-12 06:20:47",
  "company_info": {
    "name": "The Fertilisers and Chemicals Travancore Limited",
    "sector": "Basic Materials",
    "industry": "Agricultural Inputs",
    "market_cap": 585761947648,
    "current_price": 905.25,
    "pe_ratio": "N/A",
    "pb_ratio": 42.59599,
    "roe": "N/A",
    "debt_to_equity": 295.147,
    "revenue": 23325638656,
    "net_income": 1794681984,
    "eps": -0.62,
    "52_week_high": 1056.95,
    "52_week_low": 652.1,
    "dividend_yield": 0.04
  }
}