{
  "ticker": "FLAIR",
  "collected_at": "2026-06-01 06:37:16",
  "company_info": {
    "name": "Flair Writing Industries Limited",
    "sector": "Industrials",
    "industry": "Business Equipment & Supplies",
    "market_cap": 30822879232,
    "current_price": 292.45,
    "pe_ratio": 26.111609,
    "pb_ratio": 2.6984508,
    "roe": 0.13085,
    "debt_to_equity": 5.802,
    "revenue": 12708716544,
    "net_income": 1397906048,
    "eps": 11.2,
    "52_week_high": 357.0,
    "52_week_low": 245.0,
    "dividend_yield": 0.52
  }
}