{
  "ticker": "FMGOETZE",
  "collected_at": "2026-07-03 05:24:09",
  "company_info": {
    "name": "Federal-Mogul Goetze (India) Limited",
    "sector": "Consumer Cyclical",
    "industry": "Auto Parts",
    "market_cap": 25532366848,
    "current_price": 458.95,
    "pe_ratio": 14.949512,
    "pb_ratio": 1.7774018,
    "roe": 0.12438,
    "debt_to_equity": 0.068,
    "revenue": 19584020480,
    "net_income": 1706551040,
    "eps": 30.7,
    "52_week_high": 611.9,
    "52_week_low": 358.0,
    "dividend_yield": "N/A"
  }
}