{
  "ticker": "FRACTAL",
  "collected_at": "2026-06-22 07:07:23",
  "company_info": {
    "name": "Fractal Analytics Limited",
    "sector": "Technology",
    "industry": "Software - Infrastructure",
    "market_cap": 165757190144,
    "current_price": 963.9,
    "pe_ratio": 55.943127,
    "pb_ratio": 5.04269,
    "roe": 0.115839995,
    "debt_to_equity": 13.131,
    "revenue": 32996999168,
    "net_income": 2921999872,
    "eps": 17.23,
    "52_week_high": 1118.0,
    "52_week_low": 733.7,
    "dividend_yield": "N/A"
  }
}