{
  "ticker": "GFLLIMITED",
  "collected_at": "2026-06-12 06:21:50",
  "company_info": {
    "name": "GFL Limited",
    "sector": "Financial Services",
    "industry": "Asset Management",
    "market_cap": 5127798272,
    "current_price": 46.68,
    "pe_ratio": 11.385366,
    "pb_ratio": 0.20320833,
    "roe": "N/A",
    "debt_to_equity": "N/A",
    "revenue": 24961000,
    "net_income": 11732000,
    "eps": 4.1,
    "52_week_high": 81.0,
    "52_week_low": 37.25,
    "dividend_yield": "N/A"
  }
}