{
  "ticker": "GMDCLTD",
  "collected_at": "2026-06-13 06:08:35",
  "company_info": {
    "name": "Gujarat Mineral Development Corporation Limited",
    "sector": "Energy",
    "industry": "Thermal Coal",
    "market_cap": 194711388160,
    "current_price": 612.3,
    "pe_ratio": 20.36926,
    "pb_ratio": 2.7545469,
    "roe": 0.14189,
    "debt_to_equity": 4.475,
    "revenue": 26533799936,
    "net_income": 9566699520,
    "eps": 30.06,
    "52_week_high": 771.9,
    "52_week_low": 374.8,
    "dividend_yield": 1.65
  }
}