{
  "ticker": "GOCOLORS",
  "collected_at": "2026-05-30 05:21:32",
  "company_info": {
    "name": "Go Fashion (India) Limited",
    "sector": "Consumer Cyclical",
    "industry": "Apparel Retail",
    "market_cap": 16609811456,
    "current_price": 315.8,
    "pe_ratio": 23.978739,
    "pb_ratio": 2.4564788,
    "roe": 0.08529,
    "debt_to_equity": 77.141,
    "revenue": 8380093952,
    "net_income": 591761984,
    "eps": 13.17,
    "52_week_high": 919.9,
    "52_week_low": 237.05,
    "dividend_yield": "N/A"
  }
}