{
  "ticker": "GODREJAGRO",
  "collected_at": "2026-06-29 06:26:05",
  "company_info": {
    "name": "Godrej Agrovet Limited",
    "sector": "Consumer Defensive",
    "industry": "Packaged Foods",
    "market_cap": 106836729856,
    "current_price": 555.4,
    "pe_ratio": 22.614008,
    "pb_ratio": 5.2581754,
    "roe": 0.18681,
    "debt_to_equity": 72.751,
    "revenue": 102032801792,
    "net_income": 4727799808,
    "eps": 24.56,
    "52_week_high": 876.35,
    "52_week_low": 506.1,
    "dividend_yield": 1.96
  }
}