{
  "ticker": "HECPROJECT",
  "collected_at": "2026-05-22 05:54:46",
  "company_info": {
    "name": "HEC Infra Projects Limited",
    "sector": "Industrials",
    "industry": "Engineering & Construction",
    "market_cap": 1346099456,
    "current_price": 124.2,
    "pe_ratio": 10.762565,
    "pb_ratio": 2.3730366,
    "roe": "N/A",
    "debt_to_equity": 73.815,
    "revenue": 1722567040,
    "net_income": 121539000,
    "eps": 11.54,
    "52_week_high": 184.1,
    "52_week_low": 92.1,
    "dividend_yield": "N/A"
  }
}