{
  "ticker": "HIMATSEIDE",
  "collected_at": "2026-07-11 04:55:17",
  "company_info": {
    "name": "Himatsingka Seide Limited",
    "sector": "Consumer Cyclical",
    "industry": "Textile Manufacturing",
    "market_cap": 10898083840,
    "current_price": 86.67,
    "pe_ratio": 17.580122,
    "pb_ratio": 0.51980376,
    "roe": 0.029690001,
    "debt_to_equity": 123.113,
    "revenue": 25150930944,
    "net_income": 619619008,
    "eps": 4.93,
    "52_week_high": 161.7,
    "52_week_low": 72.01,
    "dividend_yield": 0.29
  }
}