{
  "ticker": "HINDPETRO",
  "collected_at": "2026-05-30 05:23:18",
  "company_info": {
    "name": "Hindustan Petroleum Corporation Limited",
    "sector": "Energy",
    "industry": "Oil & Gas Refining & Marketing",
    "market_cap": 838042910720,
    "current_price": 393.85,
    "pe_ratio": 4.6444573,
    "pb_ratio": 1.2785636,
    "roe": 0.30929002,
    "debt_to_equity": 85.369,
    "revenue": 4396334448640,
    "net_income": 180468908032,
    "eps": 84.8,
    "52_week_high": 508.45,
    "52_week_low": 316.2,
    "dividend_yield": 8.82
  }
}