{
  "ticker": "HITECHCORP",
  "collected_at": "2026-05-26 05:51:04",
  "company_info": {
    "name": "Hitech Corporation Limited",
    "sector": "Consumer Cyclical",
    "industry": "Packaging & Containers",
    "market_cap": 3437888256,
    "current_price": 200.16,
    "pe_ratio": 47.09647,
    "pb_ratio": 1.2345191,
    "roe": 0.0547,
    "debt_to_equity": 48.253,
    "revenue": 6446770176,
    "net_income": 151886000,
    "eps": 4.25,
    "52_week_high": 223.44,
    "52_week_low": 112.0,
    "dividend_yield": 0.6
  }
}