{
  "ticker": "HMVL",
  "collected_at": "2026-06-12 06:24:24",
  "company_info": {
    "name": "Hindustan Media Ventures Limited",
    "sector": "Communication Services",
    "industry": "Publishing",
    "market_cap": 5660641280,
    "current_price": 77.0,
    "pe_ratio": 4.020888,
    "pb_ratio": 0.35731027,
    "roe": 0.09039,
    "debt_to_equity": 5.347,
    "revenue": 7396400128,
    "net_income": 1410800000,
    "eps": 19.15,
    "52_week_high": 100.0,
    "52_week_low": 55.2,
    "dividend_yield": "N/A"
  }
}