{
  "ticker": "HSCL",
  "collected_at": "2026-06-30 06:01:00",
  "company_info": {
    "name": "Himadri Speciality Chemical Limited",
    "sector": "Basic Materials",
    "industry": "Specialty Chemicals",
    "market_cap": 347048935424,
    "current_price": 687.85,
    "pe_ratio": 45.856667,
    "pb_ratio": 7.3735604,
    "roe": 0.17698,
    "debt_to_equity": 16.169,
    "revenue": 46606987264,
    "net_income": 7513368064,
    "eps": 15.0,
    "52_week_high": 718.0,
    "52_week_low": 418.5,
    "dividend_yield": 0.12
  }
}