{
  "ticker": "INVENTURE",
  "collected_at": "2026-05-25 06:12:39",
  "company_info": {
    "name": "Inventure Growth & Securities Limited",
    "sector": "Financial Services",
    "industry": "Capital Markets",
    "market_cap": 1060499968,
    "current_price": 1.01,
    "pe_ratio": 25.25,
    "pb_ratio": 0.28865388,
    "roe": 0.01402,
    "debt_to_equity": 13.28,
    "revenue": 416897984,
    "net_income": 38465000,
    "eps": 0.04,
    "52_week_high": 1.8,
    "52_week_low": 0.81,
    "dividend_yield": "N/A"
  }
}