{
  "ticker": "JBMA",
  "collected_at": "2026-05-26 05:53:26",
  "company_info": {
    "name": "JBM Auto Limited",
    "sector": "Consumer Cyclical",
    "industry": "Auto Parts",
    "market_cap": 152207704064,
    "current_price": 643.6,
    "pe_ratio": 69.12996,
    "pb_ratio": 10.716486,
    "roe": "N/A",
    "debt_to_equity": 190.282,
    "revenue": 58850103296,
    "net_income": 2108814976,
    "eps": 9.31,
    "52_week_high": 790.0,
    "52_week_low": 477.0,
    "dividend_yield": 0.13
  }
}