{
  "ticker": "JSWHL",
  "collected_at": "2026-05-22 05:58:56",
  "company_info": {
    "name": "JSW Holdings Limited",
    "sector": "Industrials",
    "industry": "Conglomerates",
    "market_cap": 142326366208,
    "current_price": 12824.0,
    "pe_ratio": 100.031204,
    "pb_ratio": 0.45454744,
    "roe": "N/A",
    "debt_to_equity": "N/A",
    "revenue": 874092032,
    "net_income": 670784000,
    "eps": 128.2,
    "52_week_high": 24200.0,
    "52_week_low": 11250.0,
    "dividend_yield": "N/A"
  }
}