{
  "ticker": "JWL",
  "collected_at": "2026-06-14 06:30:00",
  "company_info": {
    "name": "Jupiter Wagons Limited",
    "sector": "Industrials",
    "industry": "Railroads",
    "market_cap": 117783281664,
    "current_price": 275.6,
    "pe_ratio": 68.55721,
    "pb_ratio": 3.9812207,
    "roe": 0.05768,
    "debt_to_equity": 33.365,
    "revenue": 29613649920,
    "net_income": 1710829056,
    "eps": 4.02,
    "52_week_high": 395.6,
    "52_week_low": 235.65,
    "dividend_yield": 0.69
  }
}