{
  "ticker": "KEC",
  "collected_at": "2026-07-24 05:08:49",
  "company_info": {
    "name": "KEC International Limited",
    "sector": "Industrials",
    "industry": "Engineering & Construction",
    "market_cap": 123956027392,
    "current_price": 465.65,
    "pe_ratio": 20.486141,
    "pb_ratio": 2.0130122,
    "roe": 0.10524999,
    "debt_to_equity": 87.306,
    "revenue": 235055398912,
    "net_income": 6055900160,
    "eps": 22.73,
    "52_week_high": 937.8,
    "52_week_low": 462.4,
    "dividend_yield": 1.15
  }
}