{
  "ticker": "KPIL",
  "collected_at": "2026-07-15 04:44:49",
  "company_info": {
    "name": "Kalpataru Projects International Limited",
    "sector": "Industrials",
    "industry": "Engineering & Construction",
    "market_cap": 222465392640,
    "current_price": 1302.7,
    "pe_ratio": 22.087147,
    "pb_ratio": 2.860719,
    "roe": 0.14513999,
    "debt_to_equity": 45.814,
    "revenue": 271430598656,
    "net_income": 10400499712,
    "eps": 58.98,
    "52_week_high": 1479.6,
    "52_week_low": 1007.1,
    "dividend_yield": 0.82
  }
}