{
  "ticker": "KSL",
  "collected_at": "2026-07-03 05:31:49",
  "company_info": {
    "name": "Kalyani Steels Limited",
    "sector": "Basic Materials",
    "industry": "Steel",
    "market_cap": 38445248512,
    "current_price": 880.7,
    "pe_ratio": 14.904384,
    "pb_ratio": 1.8265682,
    "roe": "N/A",
    "debt_to_equity": "N/A",
    "revenue": 14143579136,
    "net_income": 1217039616,
    "eps": 59.09,
    "52_week_high": 983.85,
    "52_week_low": 574.0,
    "dividend_yield": 1.13
  }
}