{
  "ticker": "LIBAS",
  "collected_at": "2026-06-01 06:45:20",
  "company_info": {
    "name": "Libas Consumer Products Limited",
    "sector": "Consumer Cyclical",
    "industry": "Apparel Manufacturing",
    "market_cap": 335103072,
    "current_price": 12.72,
    "pe_ratio": 3.6869566,
    "pb_ratio": 0.41012415,
    "roe": "N/A",
    "debt_to_equity": 16.808,
    "revenue": 922718976,
    "net_income": 23451000,
    "eps": 3.45,
    "52_week_high": 15.7,
    "52_week_low": 9.02,
    "dividend_yield": "N/A"
  }
}