{
  "ticker": "LOTUSDEV",
  "collected_at": "2026-05-22 06:01:41",
  "company_info": {
    "name": "Sri Lotus Developers and Realty Limited",
    "sector": "Industrials",
    "industry": "Engineering & Construction",
    "market_cap": 68519063552,
    "current_price": 140.2,
    "pe_ratio": 26.961538,
    "pb_ratio": 3.5774434,
    "roe": 0.17059,
    "debt_to_equity": 6.839,
    "revenue": 7689509888,
    "net_income": 2370850048,
    "eps": 5.2,
    "52_week_high": 218.49,
    "52_week_low": 102.2,
    "dividend_yield": "N/A"
  }
}