{
  "ticker": "LTTS",
  "collected_at": "2026-05-31 06:16:28",
  "company_info": {
    "name": "L&T Technology Services Limited",
    "sector": "Technology",
    "industry": "Information Technology Services",
    "market_cap": 364069814272,
    "current_price": 3432.4,
    "pe_ratio": 29.674072,
    "pb_ratio": 5.6209598,
    "roe": 0.19540001,
    "debt_to_equity": 8.911,
    "revenue": 109958995968,
    "net_income": 12280999936,
    "eps": 115.67,
    "52_week_high": 4726.0,
    "52_week_low": 3010.0,
    "dividend_yield": 1.69
  }
}