{
  "ticker": "MAGADSUGAR",
  "collected_at": "2026-05-25 06:16:33",
  "company_info": {
    "name": "Magadh Sugar & Energy Limited",
    "sector": "Consumer Defensive",
    "industry": "Confectioners",
    "market_cap": 6682251264,
    "current_price": 474.2,
    "pe_ratio": 10.526083,
    "pb_ratio": 0.8284388,
    "roe": 0.074099995,
    "debt_to_equity": 78.532,
    "revenue": 12445371392,
    "net_income": 635075968,
    "eps": 45.05,
    "52_week_high": 786.0,
    "52_week_low": 417.0,
    "dividend_yield": 2.64
  }
}