{
  "ticker": "MANAPPURAM",
  "collected_at": "2026-05-27 06:12:48",
  "company_info": {
    "name": "Manappuram Finance Limited",
    "sector": "Financial Services",
    "industry": "Credit Services",
    "market_cap": 309041594368,
    "current_price": 329.0,
    "pe_ratio": 28.071672,
    "pb_ratio": 1.7158651,
    "roe": 0.06968,
    "debt_to_equity": 360.191,
    "revenue": 41830998016,
    "net_income": 10033000448,
    "eps": 11.72,
    "52_week_high": 334.0,
    "52_week_low": 231.1,
    "dividend_yield": 0.61
  }
}