{
  "ticker": "MODIS",
  "collected_at": "2026-05-22 06:03:58",
  "company_info": {
    "name": "Modi's Navnirman Limited",
    "sector": "Real Estate",
    "industry": "Real Estate - Development",
    "market_cap": 6748189184,
    "current_price": 344.45,
    "pe_ratio": 27.12205,
    "pb_ratio": 6.390301,
    "roe": "N/A",
    "debt_to_equity": "N/A",
    "revenue": 1571250944,
    "net_income": 249543008,
    "eps": 12.7,
    "52_week_high": 415.1,
    "52_week_low": 276.0,
    "dividend_yield": "N/A"
  }
}