{
  "ticker": "MVGJL",
  "collected_at": "2026-07-15 04:48:34",
  "company_info": {
    "name": "Manoj Vaibhav Gems 'N' Jewellers Limited",
    "sector": "Consumer Cyclical",
    "industry": "Luxury Goods",
    "market_cap": 8193669632,
    "current_price": 167.74,
    "pe_ratio": 7.128772,
    "pb_ratio": 0.9840432,
    "roe": 0.14816,
    "debt_to_equity": 58.923,
    "revenue": 27440300032,
    "net_income": 1149799936,
    "eps": 23.59,
    "52_week_high": 238.8,
    "52_week_low": 129.1,
    "dividend_yield": "N/A"
  }
}