{
  "ticker": "MWL",
  "collected_at": "2026-07-13 05:19:05",
  "company_info": {
    "name": "Mangalam Worldwide Limited",
    "sector": "Basic Materials",
    "industry": "Steel",
    "market_cap": 11093201920,
    "current_price": 37.35,
    "pe_ratio": 22.10059,
    "pb_ratio": 0.3704622,
    "roe": 0.17683001,
    "debt_to_equity": 162.027,
    "revenue": 12079806464,
    "net_income": 500995008,
    "eps": 1.69,
    "52_week_high": 41.95,
    "52_week_low": 16.405,
    "dividend_yield": 0.08
  }
}