{
  "ticker": "NGLFINE",
  "collected_at": "2026-06-15 07:15:37",
  "company_info": {
    "name": "NGL Fine-Chem Limited",
    "sector": "Healthcare",
    "industry": "Drug Manufacturers - General",
    "market_cap": 19151874048,
    "current_price": 3100.0,
    "pe_ratio": 39.71813,
    "pb_ratio": 5.8167353,
    "roe": 0.15736,
    "debt_to_equity": 32.957,
    "revenue": 5009546752,
    "net_income": 481267008,
    "eps": 78.05,
    "52_week_high": 3200.0,
    "52_week_low": 980.0,
    "dividend_yield": 0.06
  }
}