{
  "ticker": "ORIENTALTL",
  "collected_at": "2026-06-09 06:06:11",
  "company_info": {
    "name": "Oriental Trimex Limited",
    "sector": "Industrials",
    "industry": "Building Products & Equipment",
    "market_cap": 475591968,
    "current_price": 6.47,
    "pe_ratio": 8.294872,
    "pb_ratio": 0.3806778,
    "roe": 0.01814,
    "debt_to_equity": 2.873,
    "revenue": 211783008,
    "net_income": 17938000,
    "eps": 0.78,
    "52_week_high": 17.6,
    "52_week_low": 4.4,
    "dividend_yield": "N/A"
  }
}