{
  "ticker": "ORIENTTECH",
  "collected_at": "2026-05-28 06:10:14",
  "company_info": {
    "name": "Orient Technologies Limited",
    "sector": "Technology",
    "industry": "Information Technology Services",
    "market_cap": 13004299264,
    "current_price": 283.9,
    "pe_ratio": 60.79229,
    "pb_ratio": 3.6543608,
    "roe": "N/A",
    "debt_to_equity": 6.129,
    "revenue": 9461533696,
    "net_income": 229960000,
    "eps": 4.67,
    "52_week_high": 466.72726,
    "52_week_low": 220.8,
    "dividend_yield": "N/A"
  }
}