{
  "ticker": "PARAS",
  "collected_at": "2026-07-24 05:17:21",
  "company_info": {
    "name": "Paras Defence and Space Technologies Limited",
    "sector": "Industrials",
    "industry": "Aerospace & Defense",
    "market_cap": 94682054656,
    "current_price": 1174.9,
    "pe_ratio": 110.21577,
    "pb_ratio": 13.039956,
    "roe": 0.13137999,
    "debt_to_equity": 3.731,
    "revenue": 4765700096,
    "net_income": 881000000,
    "eps": 10.66,
    "52_week_high": 1443.0,
    "52_week_low": 580.5,
    "dividend_yield": 0.04
  }
}