{
  "ticker": "PFIZER",
  "collected_at": "2026-07-16 05:05:21",
  "company_info": {
    "name": "Pfizer Limited",
    "sector": "Healthcare",
    "industry": "Drug Manufacturers - General",
    "market_cap": 215586193408,
    "current_price": 4712.5,
    "pe_ratio": 29.801428,
    "pb_ratio": 5.1293077,
    "roe": 0.17159,
    "debt_to_equity": 1.671,
    "revenue": 25196500992,
    "net_income": 7224300032,
    "eps": 158.13,
    "52_week_high": 5873.5,
    "52_week_low": 4360.1,
    "dividend_yield": 1.61
  }
}