{
  "ticker": "PFS",
  "collected_at": "2026-05-22 06:08:00",
  "company_info": {
    "name": "PTC India Financial Services Limited",
    "sector": "Financial Services",
    "industry": "Credit Services",
    "market_cap": 19698829312,
    "current_price": 30.67,
    "pe_ratio": 6.171026,
    "pb_ratio": 0.63820046,
    "roe": "N/A",
    "debt_to_equity": "N/A",
    "revenue": 4486537216,
    "net_income": 2449088000,
    "eps": 4.97,
    "52_week_high": 44.2,
    "52_week_low": 23.85,
    "dividend_yield": "N/A"
  }
}