{
  "ticker": "PGIL",
  "collected_at": "2026-05-27 06:17:59",
  "company_info": {
    "name": "Pearl Global Industries Limited",
    "sector": "Consumer Cyclical",
    "industry": "Apparel Manufacturing",
    "market_cap": 75492556800,
    "current_price": 1634.6,
    "pe_ratio": 27.193478,
    "pb_ratio": 5.8354607,
    "roe": 0.20896,
    "debt_to_equity": 65.567,
    "revenue": 50245976064,
    "net_income": 2776538112,
    "eps": 60.11,
    "52_week_high": 1993.3,
    "52_week_low": 1178.1,
    "dividend_yield": 1.28
  }
}