{
  "ticker": "PHOENIXLTD",
  "collected_at": "2026-06-24 05:59:10",
  "company_info": {
    "name": "The Phoenix Mills Limited",
    "sector": "Real Estate",
    "industry": "Real Estate - Diversified",
    "market_cap": 678408224768,
    "current_price": 1896.9,
    "pe_ratio": 54.21263,
    "pb_ratio": 6.1726546,
    "roe": 0.11056,
    "debt_to_equity": 37.211,
    "revenue": 44228042752,
    "net_income": 12238163968,
    "eps": 34.99,
    "52_week_high": 1993.0,
    "52_week_low": 1402.5,
    "dividend_yield": 0.14
  }
}