{
  "ticker": "POLYPLEX",
  "collected_at": "2026-06-28 06:21:22",
  "company_info": {
    "name": "Polyplex Corporation Limited",
    "sector": "Basic Materials",
    "industry": "Specialty Chemicals",
    "market_cap": 30921574400,
    "current_price": 985.0,
    "pe_ratio": 69.025925,
    "pb_ratio": 0.72929686,
    "roe": 0.00617,
    "debt_to_equity": 13.292,
    "revenue": 70858596352,
    "net_income": 449500000,
    "eps": 14.27,
    "52_week_high": 1231.7,
    "52_week_low": 740.0,
    "dividend_yield": 0.66
  }
}