{
  "ticker": "PROZONER",
  "collected_at": "2026-06-11 06:39:56",
  "company_info": {
    "name": "Prozone Realty Limited",
    "sector": "Real Estate",
    "industry": "Real Estate - Diversified",
    "market_cap": 7532478464,
    "current_price": 49.36,
    "pe_ratio": 70.51429,
    "pb_ratio": 1.5685776,
    "roe": 0.02822,
    "debt_to_equity": 134.619,
    "revenue": 1952217984,
    "net_income": 106884000,
    "eps": 0.7,
    "52_week_high": 72.77,
    "52_week_low": 34.0,
    "dividend_yield": "N/A"
  }
}