{
  "ticker": "PROZONER",
  "collected_at": "2026-06-09 06:08:08",
  "company_info": {
    "name": "Prozone Realty Limited",
    "sector": "Real Estate",
    "industry": "Real Estate - Diversified",
    "market_cap": 7735439872,
    "current_price": 50.69,
    "pe_ratio": 72.41428,
    "pb_ratio": 1.6108427,
    "roe": 0.02822,
    "debt_to_equity": 134.619,
    "revenue": 1952217984,
    "net_income": 106884000,
    "eps": 0.7,
    "52_week_high": 72.77,
    "52_week_low": 34.0,
    "dividend_yield": "N/A"
  }
}