{
  "ticker": "REDINGTON",
  "collected_at": "2026-07-20 05:30:51",
  "company_info": {
    "name": "Redington Limited",
    "sector": "Technology",
    "industry": "Information Technology Services",
    "market_cap": 212759904256,
    "current_price": 272.15,
    "pe_ratio": 14.278594,
    "pb_ratio": 2.0920775,
    "roe": 0.13089,
    "debt_to_equity": 27.26,
    "revenue": 1192660041728,
    "net_income": 14902200320,
    "eps": 19.06,
    "52_week_high": 314.4,
    "52_week_low": 191.31,
    "dividend_yield": 2.18
  }
}