{
  "ticker": "RIIL",
  "collected_at": "2026-06-24 06:01:24",
  "company_info": {
    "name": "Reliance Industrial Infrastructure Limited",
    "sector": "Industrials",
    "industry": "Engineering & Construction",
    "market_cap": 12819900416,
    "current_price": 849.0,
    "pe_ratio": 103.03398,
    "pb_ratio": 2.7051313,
    "roe": 0.02648,
    "debt_to_equity": "N/A",
    "revenue": 454200000,
    "net_income": 123900000,
    "eps": 8.24,
    "52_week_high": 993.0,
    "52_week_low": 617.35,
    "dividend_yield": 0.41
  }
}