{
  "ticker": "SEPC",
  "collected_at": "2026-06-22 07:25:30",
  "company_info": {
    "name": "SEPC Limited",
    "sector": "Industrials",
    "industry": "Engineering & Construction",
    "market_cap": 14377342976,
    "current_price": 7.39,
    "pe_ratio": 24.633331,
    "pb_ratio": 0.8148638,
    "roe": 0.031229999,
    "debt_to_equity": 18.404,
    "revenue": 10544985088,
    "net_income": 535384000,
    "eps": 0.3,
    "52_week_high": 14.4,
    "52_week_low": 4.65,
    "dividend_yield": "N/A"
  }
}