{
  "ticker": "SIRCA",
  "collected_at": "2026-07-12 05:20:34",
  "company_info": {
    "name": "Sirca Paints India Limited",
    "sector": "Basic Materials",
    "industry": "Specialty Chemicals",
    "market_cap": 22411612160,
    "current_price": 393.65,
    "pe_ratio": 33.906116,
    "pb_ratio": 4.9649367,
    "roe": 0.15767999,
    "debt_to_equity": 6.802,
    "revenue": 4924840960,
    "net_income": 650184000,
    "eps": 11.61,
    "52_week_high": 539.0,
    "52_week_low": 388.8,
    "dividend_yield": 0.38
  }
}