{
  "ticker": "SPENCERS",
  "collected_at": "2026-07-03 05:43:34",
  "company_info": {
    "name": "Spencer's Retail Limited",
    "sector": "Consumer Cyclical",
    "industry": "Department Stores",
    "market_cap": 3323243264,
    "current_price": 36.92,
    "pe_ratio": "N/A",
    "pb_ratio": -0.3643325,
    "roe": "N/A",
    "debt_to_equity": "N/A",
    "revenue": 17999982592,
    "net_income": -2493321984,
    "eps": -27.7,
    "52_week_high": 64.0,
    "52_week_low": 24.38,
    "dividend_yield": "N/A"
  }
}