{
  "ticker": "STARCEMENT",
  "collected_at": "2026-07-20 05:35:04",
  "company_info": {
    "name": "Star Cement Limited",
    "sector": "Basic Materials",
    "industry": "Building Materials",
    "market_cap": 83475382272,
    "current_price": 206.53,
    "pe_ratio": 21.204313,
    "pb_ratio": 2.618779,
    "roe": 0.12871,
    "debt_to_equity": 18.924,
    "revenue": 37764874240,
    "net_income": 3934242048,
    "eps": 9.74,
    "52_week_high": 308.95,
    "52_week_low": 196.53,
    "dividend_yield": 0.97
  }
}