{
  "ticker": "STYL",
  "collected_at": "2026-05-25 06:27:50",
  "company_info": {
    "name": "Seshaasai Technologies Limited",
    "sector": "Technology",
    "industry": "Software - Infrastructure",
    "market_cap": 44040306688,
    "current_price": 272.18,
    "pe_ratio": 19.881666,
    "pb_ratio": 3.1800816,
    "roe": 0.23236,
    "debt_to_equity": 5.865,
    "revenue": 14411350016,
    "net_income": 2400100096,
    "eps": 13.69,
    "52_week_high": 437.45,
    "52_week_low": 209.11,
    "dividend_yield": "N/A"
  }
}