{
  "ticker": "SVLL",
  "collected_at": "2026-06-24 06:05:57",
  "company_info": {
    "name": "Shree Vasu Logistics Limited",
    "sector": "Industrials",
    "industry": "Trucking",
    "market_cap": 8188686848,
    "current_price": 712.45,
    "pe_ratio": 187.48685,
    "pb_ratio": 20.551838,
    "roe": 0.15578,
    "debt_to_equity": 529.731,
    "revenue": 2239873024,
    "net_income": 57766000,
    "eps": 3.8,
    "52_week_high": 897.45,
    "52_week_low": 445.15,
    "dividend_yield": "N/A"
  }
}