{
  "ticker": "TEGA",
  "collected_at": "2026-06-24 06:06:44",
  "company_info": {
    "name": "Tega Industries Limited",
    "sector": "Industrials",
    "industry": "Specialty Industrial Machinery",
    "market_cap": 129152016384,
    "current_price": 1719.1,
    "pe_ratio": 83.98144,
    "pb_ratio": 3.8208592,
    "roe": 0.05939,
    "debt_to_equity": 11.693,
    "revenue": 16919359488,
    "net_income": 1426530048,
    "eps": 20.47,
    "52_week_high": 2125.0,
    "52_week_low": 1467.0,
    "dividend_yield": 0.12
  }
}