{
  "ticker": "TEXMOPIPES",
  "collected_at": "2026-06-22 07:29:29",
  "company_info": {
    "name": "Texmo Pipes and Products Limited",
    "sector": "Industrials",
    "industry": "Building Products & Equipment",
    "market_cap": 1328080640,
    "current_price": 45.49,
    "pe_ratio": 9.556723,
    "pb_ratio": 0.65000576,
    "roe": "N/A",
    "debt_to_equity": 23.807,
    "revenue": 3768580096,
    "net_income": 184404992,
    "eps": 4.76,
    "52_week_high": 68.99,
    "52_week_low": 33.0,
    "dividend_yield": "N/A"
  }
}