{
  "ticker": "THEMISMED",
  "collected_at": "2026-07-24 05:28:29",
  "company_info": {
    "name": "Themis Medicare Limited",
    "sector": "Healthcare",
    "industry": "Drug Manufacturers - Specialty & Generic",
    "market_cap": 10069513216,
    "current_price": 108.41,
    "pe_ratio": 903.4167,
    "pb_ratio": 2.5174744,
    "roe": 0.0028600001,
    "debt_to_equity": 25.112,
    "revenue": 3422354944,
    "net_income": 11439000,
    "eps": 0.12,
    "52_week_high": 148.0,
    "52_week_low": 64.95,
    "dividend_yield": 0.46
  }
}