{
  "ticker": "THOMASCOTT",
  "collected_at": "2026-07-08 05:16:50",
  "company_info": {
    "name": "Thomas Scott (India) Limited",
    "sector": "Consumer Cyclical",
    "industry": "Textile Manufacturing",
    "market_cap": 4761271808,
    "current_price": 324.55,
    "pe_ratio": 24.329084,
    "pb_ratio": 3.3693225,
    "roe": 0.15872,
    "debt_to_equity": 33.824,
    "revenue": 2548858112,
    "net_income": 193044992,
    "eps": 13.34,
    "52_week_high": 459.8,
    "52_week_low": 230.0,
    "dividend_yield": "N/A"
  }
}