{
  "ticker": "TOUCHWOOD",
  "collected_at": "2026-06-06 05:45:12",
  "company_info": {
    "name": "Touchwood Entertainment Limited",
    "sector": "Communication Services",
    "industry": "Advertising Agencies",
    "market_cap": 780784576,
    "current_price": 70.46,
    "pe_ratio": 16.310184,
    "pb_ratio": 1.8690646,
    "roe": 0.094399996,
    "debt_to_equity": 7.901,
    "revenue": 745801024,
    "net_income": 40485000,
    "eps": 4.32,
    "52_week_high": 136.59,
    "52_week_low": 63.0,
    "dividend_yield": "N/A"
  }
}