{
  "ticker": "TPLPLASTEH",
  "collected_at": "2026-06-05 06:30:18",
  "company_info": {
    "name": "TPL Plastech Limited",
    "sector": "Consumer Cyclical",
    "industry": "Packaging & Containers",
    "market_cap": 5265982464,
    "current_price": 67.51,
    "pe_ratio": 18.099195,
    "pb_ratio": 3.4533737,
    "roe": 0.18370001,
    "debt_to_equity": 11.202,
    "revenue": 4225533952,
    "net_income": 290707008,
    "eps": 3.73,
    "52_week_high": 87.69,
    "52_week_low": 50.01,
    "dividend_yield": 1.46
  }
}