{
  "ticker": "TRANSPEK",
  "collected_at": "2026-06-16 07:31:54",
  "company_info": {
    "name": "Transpek Industry Limited",
    "sector": "Basic Materials",
    "industry": "Chemicals",
    "market_cap": 5558758400,
    "current_price": 995.2,
    "pe_ratio": 12.176679,
    "pb_ratio": 0.72408885,
    "roe": "N/A",
    "debt_to_equity": "N/A",
    "revenue": 6211990016,
    "net_income": 456454016,
    "eps": 81.73,
    "52_week_high": 1269.0,
    "52_week_low": 961.0,
    "dividend_yield": "N/A"
  }
}