{
  "ticker": "UNICHEMLAB",
  "collected_at": "2026-06-02 06:45:15",
  "company_info": {
    "name": "Unichem Laboratories Limited",
    "sector": "Healthcare",
    "industry": "Drug Manufacturers - Specialty & Generic",
    "market_cap": 25659377664,
    "current_price": 364.45,
    "pe_ratio": 10.16597,
    "pb_ratio": 1.0530833,
    "roe": 0.097849995,
    "debt_to_equity": 18.405,
    "revenue": 22649100288,
    "net_income": 2528399872,
    "eps": 35.85,
    "52_week_high": 666.6,
    "52_week_low": 278.2,
    "dividend_yield": "N/A"
  }
}