{
  "ticker": "VISHNU",
  "collected_at": "2026-06-22 07:32:01",
  "company_info": {
    "name": "Vishnu Chemicals Limited",
    "sector": "Basic Materials",
    "industry": "Specialty Chemicals",
    "market_cap": 42607206400,
    "current_price": 632.95,
    "pe_ratio": 29.91257,
    "pb_ratio": 4.263553,
    "roe": 0.14218001,
    "debt_to_equity": 49.066,
    "revenue": 16096989184,
    "net_income": 1422710016,
    "eps": 21.16,
    "52_week_high": 652.0,
    "52_week_low": 443.7,
    "dividend_yield": 0.05
  }
}