{
  "ticker": "WELSPUNLIV",
  "collected_at": "2026-06-06 05:47:27",
  "company_info": {
    "name": "Welspun Living Limited",
    "sector": "Consumer Cyclical",
    "industry": "Textile Manufacturing",
    "market_cap": 136810094592,
    "current_price": 143.13,
    "pe_ratio": 66.57209,
    "pb_ratio": 2.9609632,
    "roe": 0.04301,
    "debt_to_equity": 46.501,
    "revenue": 93991100416,
    "net_income": 2044400000,
    "eps": 2.15,
    "52_week_high": 152.85,
    "52_week_low": 107.1,
    "dividend_yield": 0.07
  }
}