{
  "ticker": "WSI",
  "collected_at": "2026-07-20 05:40:16",
  "company_info": {
    "name": "W.S. Industries (India) Limited",
    "sector": "Industrials",
    "industry": "Engineering & Construction",
    "market_cap": 4639480832,
    "current_price": 61.13,
    "pe_ratio": 185.24242,
    "pb_ratio": 1.0551845,
    "roe": 0.00749,
    "debt_to_equity": 17.361,
    "revenue": 915000000,
    "net_income": 26000000,
    "eps": 0.33,
    "52_week_high": 98.9,
    "52_week_low": 59.25,
    "dividend_yield": "N/A"
  }
}