{
  "ticker": "YATHARTH",
  "collected_at": "2026-06-04 06:51:46",
  "company_info": {
    "name": "Yatharth Hospital & Trauma Care Services Limited",
    "sector": "Healthcare",
    "industry": "Medical Care Facilities",
    "market_cap": 78326464512,
    "current_price": 812.9,
    "pe_ratio": 44.566887,
    "pb_ratio": 4.6384106,
    "roe": 0.09889,
    "debt_to_equity": 14.614,
    "revenue": 12329589760,
    "net_income": 1753799936,
    "eps": 18.24,
    "52_week_high": 889.9,
    "52_week_low": 485.0,
    "dividend_yield": "N/A"
  }
}